ao3/__init__.py
ao3/users.py
ao3/utils.py
ao3/works.py
ao3-0.2.0.dist-info/DESCRIPTION.rst
ao3-0.2.0.dist-info/METADATA
ao3-0.2.0.dist-info/metadata.json
ao3-0.2.0.dist-info/RECORD
ao3-0.2.0.dist-info/top_level.txt
ao3-0.2.0.dist-info/WHEEL
