Metadata-Version: 2.0
Name: ao3
Version: 0.2.0
Summary: A Python API for scraping AO3 (the Archive of Our Own)
Home-page: https://github.com/alexwlchan/ao3
Author: Alex Chan
Author-email: alex@alexwlchan.net
License: MIT
Platform: UNKNOWN
Classifier: Development Status :: 3 - Alpha
Classifier: Intended Audience :: Other Audience
Classifier: License :: OSI Approved :: MIT License
Classifier: Programming Language :: Python :: 2
Classifier: Programming Language :: Python :: 2.7
Classifier: Programming Language :: Python :: 3
Classifier: Programming Language :: Python :: 3.3
Classifier: Programming Language :: Python :: 3.4
Classifier: Programming Language :: Python :: 3.5
Classifier: Programming Language :: Python :: 3.6
Requires-Dist: beautifulsoup4 (>=4.5.3,<5)
Requires-Dist: requests (>=2.12.4,<3)
